{
  "id": "earrings-222",
  "title": "Contemporary Diamond-Studded Hoop Earrings - Trendy Kammalu",
  "category": "earrings",
  "original_type": "Earrings",
  "materials": [
    "18K Yellow Gold",
    "Round Brilliant Cut Diamonds (Clarity VS1",
    "Color G)",
    "High Polish Finish"
  ],
  "features": "Modern hoop design with equidistant diamond settings along the circumference. Minimalist aesthetic for a contemporary look. Seamless and comfortable latch closure.",
  "colors": [
    "Warm yellow gold with sparkling white diamonds."
  ],
  "occasions": [
    "Everyday wear",
    "casual gatherings",
    "office",
    "parties",
    "cocktails",
    "anniversary gifts. Suitable for both traditional and modern attire."
  ],
  "description": "Versatile and stylish design that complements any outfit. High-quality diamonds for exceptional brilliance and sparkle. Lightweight and comfortable for extended wear. A modern twist on classic gold kammalu, perfect for the modern South Indian woman.",
  "tags": [
    "Earrings",
    "Kammalu",
    "Hoop Earrings",
    "Diamond Earrings",
    "Gold Earrings",
    "Contemporary Jewelry",
    "Modern Indian Jewelry",
    "South Indian Jewelry",
    "Telugu Jewelry",
    "Hyderabadi Jewelry",
    "Fashion Earrings",
    "Daily Wear",
    "Gift for Her"
  ],
  "original_id": "diamond_jewellery_IMG-20241130-WA0148_0764",
  "collection": "diamond"
}