{
  "id": "earrings-029",
  "title": "Navaratna Stud Earrings - A Timeless Telugu Treasure",
  "category": "earrings",
  "original_type": "Earrings",
  "materials": [
    "22K Gold (916 Hallmark)",
    "Authentic Navaratna Gemstones (Ruby",
    "Pearl",
    "Coral",
    "Emerald",
    "Yellow Sapphire",
    "Diamond",
    "Blue Sapphire",
    "Garnet",
    "Cat's Eye)",
    "Brilliant-cut Cubic Zirconia (CZ). Features a lustrous Hyderabadi Polish."
  ],
  "features": "Intricately designed floral motif setting. The 'Navaratna' (nine gems) setting is meticulously placed, each stone representing a celestial body and believed to bring prosperity and ward off negativity. The framework is gracefully adorned with sparkling CZ stones, adding a touch of modern glamour to the traditional design. The openwork design allows for light to beautifully illuminate the gems.",
  "colors": [
    "Predominantly gold",
    "with a vibrant mix of gemstone colors: ruby (red)",
    "pearl (white)",
    "coral (orange/red)",
    "emerald (green)",
    "yellow sapphire (yellow)",
    "diamond (clear)",
    "blue sapphire (blue)",
    "garnet (deep red)",
    "and cat's eye (grey/green)."
  ],
  "occasions": [
    "Ideal for festive occasions",
    "traditional ceremonies like weddings (Veedukolu)",
    "anniversaries",
    "and as a valuable heirloom piece. Suitable for adding a touch of elegance to contemporary outfits as well."
  ],
  "description": "A classic Navaratna design, handcrafted with exceptional skill. The Navaratna stones are believed to have astrological significance, making this a powerful and auspicious piece. The high-quality gold and gemstones ensure lasting beauty and value. The Hyderabadi Polish adds a unique luster, enhancing the overall appeal. Perfect blend of tradition and contemporary aesthetics.",
  "tags": [
    "Navaratna Earrings",
    "Stud Earrings",
    "Gold Earrings",
    "South Indian Jewelry",
    "Telugu Jewelry",
    "Hyderabad Jewelry",
    "Traditional Jewelry",
    "Navarathnalu",
    "Gemstone Jewelry",
    "Wedding Jewelry",
    "Festival Jewelry",
    "Indian Jewelry",
    "CZ Earrings",
    "22K Gold",
    "Hyderabadi Polish",
    "ethnic jewelry",
    "auspicious jewelry."
  ],
  "original_id": "diamond_jewellery_384d3e9d-2ce4-4c71-93e2-b0b757694c2f_0100",
  "collection": "diamond"
}