{
  "id": "necklaces-797",
  "title": "Diamond Cascade Haaram - A Dazzling Statement",
  "category": "necklaces",
  "original_type": "Necklace",
  "materials": [
    "18K White Gold. Features 101 brilliant-cut Diamonds (3.46ct total weight)",
    "including Pan cut",
    "a mix of full-cut",
    "and marquise cut stones",
    "all meticulously selected for clarity and fire. Total gold weight: 69.190 grams."
  ],
  "features": "A layered cascade design with pear-shaped and round diamonds creating a shimmering waterfall effect. The diamonds are set in a prong setting to maximize their brilliance. The intricate design ensures maximum light reflection, enhancing the fire of each diamond.",
  "colors": [
    "Brilliant White (Diamonds) and White Gold."
  ],
  "occasions": [
    "Perfect for weddings (Muhurtham)",
    "receptions",
    "and grand celebrations. Also suitable for upscale parties and formal events where a touch of glamour is desired."
  ],
  "description": "This Diamond Cascade Haaram is a showstopper. The exquisite craftsmanship and brilliant diamonds make it a timeless investment piece. Its bold and modern design paired with its traditional Haaram form makes it uniquely desirable. This necklace is sure to turn heads and become a cherished heirloom. The variety of diamond cuts adds dimension and visual interest.",
  "tags": [
    "Diamond Haaram",
    "White Gold Necklace",
    "South Indian Jewelry",
    "Wedding Jewelry",
    "Hyderabad Jewelry",
    "Reception Necklace",
    "Diamond Jewelry",
    "Bridal Jewelry",
    "కంఠాభరణం",
    "Vaddanam",
    "Mutyala Haram",
    "Precious Stone Jewelry"
  ],
  "original_id": "diamond_jewellery_PHOTO-2024-06-01-16-34-46 3_1390",
  "collection": "diamond"
}