{
  "id": "earrings-078",
  "title": "Kasula Jhumkaalu with Polki Diamonds and Gem Accents",
  "category": "earrings",
  "original_type": "Earrings",
  "materials": [
    "22K Gold",
    "Uncut Polki Diamonds",
    "Ruby",
    "Emerald. Hyderabadi Polish for a lasting luster."
  ],
  "features": "Intricately crafted lattice Jhumka design, embellished with dazzling Polki diamonds. Features a floral stud design with a central Emerald gemstone. Delicate gold bead hangings at the bottom provide graceful movement. The Jhumka body showcases an ornate filigree pattern adorned with smaller Polki diamonds and a central Ruby, adding a pop of color.",
  "colors": [
    "Gold",
    "White (Polki Diamonds)",
    "Red (Ruby)",
    "Green (Emerald)"
  ],
  "occasions": [
    "Ideal for weddings (Muhurtham)",
    "festive celebrations (Sankranthi",
    "Ugadi)",
    "and traditional South Indian events like Seemantham",
    "half-saree function (Voni Function) and other special occasions. Also a perfect statement piece for any evening event."
  ],
  "description": "These Jhumkaalu represent the pinnacle of South Indian jewelry craftsmanship, blending traditional design with modern sensibilities. The use of uncut Polki diamonds adds a unique, timeless appeal. The exquisite detailing and Hyderabadi polish ensure lasting beauty and heirloom quality. These earrings capture the essence of Telugu culture and are sure to make a statement.",
  "tags": [
    "Jhumka",
    "Jhumkaalu",
    "Polki",
    "Diamonds",
    "South Indian Jewelry",
    "Telugu Jewelry",
    "Traditional Earrings",
    "Wedding Jewelry",
    "Hyderabadi Jewelry",
    "Gold Earrings",
    "Kasula Jhumka",
    "Ethnic Jewelry",
    "Temple Jewelry",
    "Festive Jewelry",
    "Voni Function Jewelry"
  ],
  "original_id": "diamond_jewellery_a26475df-1f20-411d-aeac-8f446b020f0b_0170",
  "collection": "diamond"
}