{
  "id": "bangles-027",
  "title": "Kundan Diamond Zig-Zag Vanki Bangle - Contemporary Design",
  "category": "bangles",
  "original_type": "Bangle",
  "materials": [
    "22K Yellow Gold with Hyderabadi Polish",
    "Kundan Diamonds (estimated SI Clarity)",
    "Open Cuff Design"
  ],
  "features": "A sleek and modern take on the traditional Vanki. Features a distinct zig-zag pattern meticulously crafted in 22K gold. The geometric design is accentuated with strategically placed Kundan diamonds within each segment, adding a touch of brilliance. The open cuff design allows for comfortable and easy wear.",
  "colors": [
    "Warm Yellow Gold",
    "Sparkling White Diamonds"
  ],
  "occasions": [
    "Perfect for contemporary celebrations",
    "cocktail parties",
    "and adding a touch of modern elegance to traditional attire. Can be worn for pre-wedding functions (like Sangeet)",
    "festive gatherings",
    "or as a statement piece for special occasions."
  ],
  "description": "A unique blend of traditional craftsmanship and modern design. The Kundan diamonds offer a classic sparkle, while the zig-zag pattern adds a contemporary flair. Crafted with high-quality 22K gold and finished with the renowned Hyderabadi polish for lasting shine and durability. This Vanki bangle is a true statement piece that will elevate any outfit. It's durable and has cultural significance for its origin from Hyderabadi artisans.",
  "tags": [
    "Bangle",
    "Vanki",
    "Kada",
    "Diamond Bangle",
    "Kundan",
    "Gold Bangle",
    "Hyderabadi Jewelry",
    "South Indian Jewelry",
    "Geometric Jewelry",
    "Contemporary Bangle",
    "Wedding Jewelry",
    "Festive Jewelry",
    "Open Cuff",
    "Zig-Zag Design",
    "Women's Jewelry",
    "Jewellery"
  ],
  "original_id": "bangles_IMG-20240902-WA0035_1643",
  "collection": "bangles"
}