{
  "id": "necklaces-679",
  "title": "Delicate Diamond Petal Haaram - A Touch of Sparkle",
  "category": "necklaces",
  "original_type": "Necklace",
  "materials": [
    "18K Rose Gold",
    "ethically sourced Diamonds (VVS clarity",
    "brilliant cut). Hyderabadi Polish for lasting brilliance."
  ],
  "features": "This contemporary Haaram features a delicate chain of intertwined geometric motifs, each set with sparkling pavé diamonds. A striking floral pendant adorned with diamonds completes the design. The minimalist style blends seamlessly with traditional and modern attire.",
  "colors": [
    "Rose Gold",
    "White (Diamonds)"
  ],
  "occasions": [
    "Perfect for cocktail parties",
    "engagement parties",
    "anniversaries",
    "or as a sophisticated everyday accessory. Can also be worn for contemporary Mehendi or Sangeet functions."
  ],
  "description": "This exquisite Haaram offers a modern twist on classic South Indian jewelry. The brilliant diamonds and subtle rose gold hue complement any skin tone, while the lightweight design ensures comfortable wear. It's a timeless piece that reflects your refined taste and appreciation for understated elegance.",
  "tags": [
    "Diamond Necklace",
    "Haaram",
    "Rose Gold",
    "South Indian Jewelry",
    "Hyderabadi Jewelry",
    "Bridal Jewelry",
    "Modern Jewelry",
    "Contemporary Design",
    "Wedding Jewelry",
    "cocktail Jewellery",
    "Engagement",
    "anniversary"
  ],
  "original_id": "diamond_jewellery_PHOTO-2024-05-18-12-40-47 2_1185",
  "collection": "diamond"
}