{
  "id": "earrings-598",
  "title": "Floral Zircon Jhumka Earrings",
  "category": "earrings",
  "original_type": "Earrings",
  "materials": [
    "Base metal alloy (believed to be gold plated); Zircon stones in various colors."
  ],
  "features": "Floral motif, delicate gemstone setting, mixed color palette. The jhumka design offers a modern twist with its floral arrangement and zircon detailing. Likely features a secure push-back closure for comfort and ease of wear. There is a scroll design on the top portion of the earring.",
  "colors": [
    "Silver",
    "pink",
    "yellow",
    "and blue zircon stones. The base metal appears silver."
  ],
  "occasions": [
    "Suitable for parties",
    "festivals",
    "weddings",
    "or casual wear",
    "adding a touch of elegance to any outfit."
  ],
  "description": "Combines classic Indian design with modern aesthetics; The multiple colored stones make these jhumkas match with a variety of outfits; Lightweight and comfortable for extended wear.",
  "tags": [
    "Earrings",
    "Jhumka",
    "Zircon",
    "Floral",
    "Indian Jewelry",
    "South Indian Jewelry",
    "Party Wear",
    "Wedding Jewelry",
    "Fashion Jewelry"
  ],
  "original_id": "sjpl_PHOTO-2023-11-27-12-30-44 2-1_1817",
  "collection": "sjpl"
}