{
  "id": "necklaces-599",
  "title": "Contemporary Diamond Mangalsutra - Nalla Pusala Dandalu",
  "category": "necklaces",
  "original_type": "Necklace",
  "materials": [
    "Base metal alloy with rose gold polish",
    "Round brilliant cut cubic zirconia",
    "Black onyx beads."
  ],
  "features": "Delicate chain interspersed with traditional black onyx beads. Features a central, round pendant paved with sparkling cubic zirconia stones. Modern take on the traditional mangalsutra, offering a lighter, everyday wear option.",
  "colors": [
    "Rose Gold",
    "Black",
    "White (Cubic Zirconia)"
  ],
  "occasions": [
    "Daily wear",
    "anniversary",
    "modern celebrations",
    "gift for wife",
    "festivals",
    "casual occasions."
  ],
  "description": "A modern interpretation of the sacred Mangalsutra, this piece beautifully blends tradition and contemporary style. The dazzling cubic zirconia pendant adds a touch of elegance while maintaining the cultural significance of the Nalla Pusalu (black beads). Crafted with high-quality materials for lasting beauty and comfortable wear. Perfect for the modern woman who values tradition.",
  "tags": [
    "Mangalsutra",
    "Pusala Dandalu",
    "Rose Gold",
    "Diamond Pendant",
    "Cubic Zirconia",
    "Black Beads",
    "Modern Jewelry",
    "Indian Jewelry",
    "Contemporary Design",
    "Wedding Jewelry",
    "Anniversary Gift"
  ],
  "original_id": "diamond_jewellery_PHOTO-2024-04-26-13-41-22 3_1086",
  "collection": "diamond"
}