{
  "id": "necklaces-153",
  "title": "Vaidooryam Haaralu: Emerald Bead Necklace with Antique Gold Pendant",
  "category": "necklaces",
  "original_type": "Necklace",
  "materials": [
    "22K Gold",
    "Natural Emerald beads (Panche Palla)",
    "Faceted Ruby",
    "Uncut Diamonds (Polki)",
    "Hyderabadi Polish"
  ],
  "features": "This exquisite haaram features seven strands of meticulously strung emerald beads. The pendant is crafted in antique gold using traditional nakshi work techniques and set with polki diamonds. The central ruby exhibits a beautiful carved pattern. The pendant is designed in a floral motif with emerald accents.",
  "colors": [
    "Emerald Green",
    "Ruby Pink",
    "Gold",
    "White (Diamonds)"
  ],
  "occasions": [
    "Weddings (Vivahaalu)",
    "Engagements (Nischitartham)",
    "Seemantham",
    "Half-Saree Function (Voni Function)",
    "Grand Festivals",
    "Family Celebrations"
  ],
  "description": "A testament to Hyderabad's rich jewelry heritage, this haaram combines the auspiciousness of emeralds with the opulence of antique gold. The meticulous craftsmanship and high-quality gemstones make it a timeless heirloom. The Hyderabadi polish enhances the gold's luster, ensuring lasting beauty.",
  "tags": [
    "Haaram",
    "Emerald Necklace",
    "Panche Palla",
    "Ruby",
    "Polki Diamonds",
    "Antique Gold",
    "Nakshi Work",
    "South Indian Jewelry",
    "Telugu Jewelry",
    "Traditional Jewelry",
    "Wedding Jewelry",
    "Hyderabadi Jewelry",
    "Temple Jewelry",
    "Vaidooryam"
  ],
  "original_id": "diamond_jewellery_DPPD8-174_0386",
  "collection": "diamond"
}